pepyno/__init__.py
pepyno/cli.py
pepyno/constants.py
pepyno/converter.py
pepyno/logger.py
pepyno/tools.py
pepyno-1.0.3.dist-info/LICENSE
pepyno-1.0.3.dist-info/METADATA
pepyno-1.0.3.dist-info/WHEEL
pepyno-1.0.3.dist-info/entry_points.txt
pepyno-1.0.3.dist-info/top_level.txt
pepyno-1.0.3.dist-info/RECORD
