Metadata-Version: 2.2
Name: pepyno
Version: 1.0.3
Summary: A tool to convert Behave tests into Cucumber format.
Keywords: setuptools,development,cucumber,behave,json
Classifier: Programming Language :: Python :: 3
Classifier: Programming Language :: Python :: 3.11
Classifier: License :: OSI Approved :: MIT License
Classifier: Operating System :: OS Independent
Classifier: Intended Audience :: Developers
Classifier: Topic :: Software Development :: Testing
Requires-Python: >=3.11
License-File: LICENSE
Requires-Dist: click>=8.1.8
